shuku/__init__.py
shuku/cli.py
shuku/config.py
shuku/demo_utils.py
shuku/logging_setup.py
shuku/utils.py
shuku-0.0.7.dist-info/METADATA
shuku-0.0.7.dist-info/WHEEL
shuku-0.0.7.dist-info/entry_points.txt
shuku-0.0.7.dist-info/licenses/COPYING
shuku-0.0.7.dist-info/RECORD
