Metadata-Version: 2.4
Name: shuku
Version: 0.0.7
Summary: A command-line tool for condensing video and audio files based on subtitle timestamps, optimizing media content for language learning and study.
License: GPL-3.0-or-later
License-File: COPYING
Keywords: media-condensation,video,audio,subtitle,subtitles,condenser,language learning,immersion learning,summarization
Author: Óscar Fernández
Author-email: osc@osc.garden
Requires-Python: >=3.11,<4.0
Classifier: Development Status :: 3 - Alpha
Classifier: Environment :: Console
Classifier: Intended Audience :: Education
Classifier: Intended Audience :: End Users/Desktop
Classifier: License :: OSI Approved :: GNU General Public License v3 or later (GPLv3+)
Classifier: Operating System :: OS Independent
Classifier: Programming Language :: Python :: 3
Classifier: Programming Language :: Python :: 3.11
Classifier: Programming Language :: Python :: 3.12
Classifier: Programming Language :: Python :: 3.13
Classifier: Programming Language :: Python :: 3.14
Classifier: Topic :: Education
Classifier: Topic :: Multimedia :: Sound/Audio :: Speech
Classifier: Topic :: Multimedia :: Video
Requires-Dist: pysubs2 (>=1.7.3,<2.0.0)
Requires-Dist: python-ffmpeg (>=2.0.12,<3.0.0)
Project-URL: Documentation, https://github.com/welpo/shuku
Project-URL: Homepage, https://github.com/welpo/shuku
Project-URL: Repository, https://github.com/welpo/shuku
